tweetynet/__about__.py
tweetynet/__init__.py
tweetynet/model.py
tweetynet/network.py
tweetynet-0.9.0.dist-info/entry_points.txt
tweetynet-0.9.0.dist-info/LICENSE
tweetynet-0.9.0.dist-info/WHEEL
tweetynet-0.9.0.dist-info/METADATA
tweetynet-0.9.0.dist-info/RECORD
