Metadata-Version: 2.1
Name: tweetynet
Version: 0.9.0
Summary: neural network that segments and labels birdsong and other animal vocalizations
Author-email: Yarden Cohen <yardencsgithub@users.noreply.github.com>, David Nicholson <nickledave@users.noreply.github.com>
Requires-Python: >=3.8
Classifier: License :: OSI Approved :: BSD License
Classifier: Development Status :: 5 - Production/Stable
Classifier: Programming Language :: Python
Classifier: Programming Language :: Python :: 3
Classifier: Programming Language :: Python :: 3.8
Classifier: Programming Language :: Python :: 3.9
Classifier: Programming Language :: Python :: 3.10
Classifier: Programming Language :: Python :: Implementation :: CPython
Requires-Dist: torch>=1.7.1
Requires-Dist: vak>=0.8.0
Requires-Dist: flit ; extra == "dev"
Requires-Dist: ipython>=7.30.1 ; extra == "dev"
Requires-Dist: nox ; extra == "dev"
Requires-Dist: pytest >=2.7.3 ; extra == "test"
Requires-Dist: pytest-cov ; extra == "test"
Project-URL: Source, https://github.com/yardencsGitHub/tweetynet
Provides-Extra: dev
Provides-Extra: test
